browserid/__init__.py
browserid/browser_id.py
browserid/pages/__init__.py
browserid/pages/base.py
browserid/pages/complete_registration.py
browserid/pages/reset_password.py
browserid/pages/sign_in.py
browserid-1.4.dist-info/DESCRIPTION.rst
browserid-1.4.dist-info/METADATA
browserid-1.4.dist-info/RECORD
browserid-1.4.dist-info/WHEEL
browserid-1.4.dist-info/metadata.json
browserid-1.4.dist-info/pbr.json
browserid-1.4.dist-info/top_level.txt
