Metadata-Version: 2.0
Name: browserid
Version: 1.4
Summary: Mozilla BrowserID (Persona) Page Object Model
Home-page: https://github.com/mozilla/bidpom
Author: Mozilla Web QA
Author-email: mozwebqa@mozilla.org
License: MPL 2.0
Keywords: mozilla
Platform: UNKNOWN
